better_tree/__init__.py
better_tree/__main__.py
better_tree/console.py
better_tree/main.py
LICENSE
better_tree-0.1.0.dist-info/entry_points.txt
better_tree-0.1.0.dist-info/LICENSE
better_tree-0.1.0.dist-info/WHEEL
better_tree-0.1.0.dist-info/METADATA
better_tree-0.1.0.dist-info/RECORD
